LICENSE
MANIFEST.in
README.md
setup.py
hapdoc/__init__.py
hapdoc/__main__.py
hapdoc/hapdoc.py
hapdoc/utils.py
hapdoc.egg-info/PKG-INFO
hapdoc.egg-info/SOURCES.txt
hapdoc.egg-info/dependency_links.txt
hapdoc.egg-info/entry_points.txt
hapdoc.egg-info/requires.txt
hapdoc.egg-info/top_level.txt
hapdoc/autodocker/__init__.py
hapdoc/autodocker/abc.py
hapdoc/autodocker/filetypes/__init__.py
hapdoc/autodocker/filetypes/fastapi.py
hapdoc/autodocker/filetypes/js.py
hapdoc/autodocker/filetypes/py.py
hapdoc/md/__init__.py
hapdoc/templates/vitepress/index.html