Metadata-Version: 2.1
Name: hapdoc
Version: 1.9.9
Summary: autodoc tool for everything
Home-page: https://github.com/HapticX/hapdoc
Author: Ethosa
Author-email: social.ethosa@gmail.com
Maintainer: HapticX
Maintainer-email: hapticx.company@gmail.com
License: MIT
Platform: UNKNOWN
Classifier: Development Status :: 5 - Production/Stable
Classifier: Environment :: Console
Classifier: Framework :: FastAPI
Classifier: License :: OSI Approved :: MIT License
Classifier: Operating System :: OS Independent
Classifier: Programming Language :: Python :: 3.10
Classifier: Programming Language :: Python :: 3.11
Classifier: Programming Language :: Python :: 3.12
Classifier: Topic :: Documentation
Classifier: Topic :: Software Development :: Documentation
License-File: LICENSE
